flask_feature_flag/__init__.py
flask_feature_flag/flag.py
flask_feature_flag/models.py
flask_feature_flag/repository.py
flask_feature_flag/use_cases.py
flask_feature_flag/utils.py
flask_feature_flag-0.2.1.dist-info/LICENSE
flask_feature_flag-0.2.1.dist-info/METADATA
flask_feature_flag-0.2.1.dist-info/WHEEL
flask_feature_flag-0.2.1.dist-info/top_level.txt
flask_feature_flag-0.2.1.dist-info/RECORD
