Metadata-Version: 2.1
Name: flask-feature-flag
Version: 0.2.1
Summary: Flask feature flag
Home-page: https://gitlab.com/terminus-zinobe/flask-feature-flag
Author: Terminus
Author-email: jose.salas@zinobe.com
License: UNKNOWN
Platform: UNKNOWN
Classifier: Programming Language :: Python :: 3
Classifier: License :: OSI Approved :: MIT License
Classifier: Operating System :: OS Independent
Requires-Python: >=3.6
Requires-Dist: flask (>=1.1.1)
Requires-Dist: flask-mongoengine (>=0.9.5)
Requires-Dist: Flask-Caching (>=1.8.0)
Requires-Dist: constants-and-utils (>=0.0.1)
